{
  "openapi": "3.0.1",
  "info": {
    "title": "Chess.TLDevProject",
    "version": "1.0"
  },
  "paths": {
    "/api/Game/start": {
      "post": {
        "tags": [
          "Game"
        ],
        "requestBody": {
          "content": {
            "application/json": {
              "schema": {
                "$ref": "#/components/schemas/Match"
              }
            },
            "text/json": {
              "schema": {
                "$ref": "#/components/schemas/Match"
              }
            },
            "application/*+json": {
              "schema": {
                "$ref": "#/components/schemas/Match"
              }
            }
          }
        },
        "responses": {
          "200": {
            "description": "OK"
          }
        }
      }
    },
    "/api/Game/restart": {
      "post": {
        "tags": [
          "Game"
        ],
        "requestBody": {
          "content": {
            "application/json": {
              "schema": {
                "type": "integer",
                "format": "int32"
              }
            },
            "text/json": {
              "schema": {
                "type": "integer",
                "format": "int32"
              }
            },
            "application/*+json": {
              "schema": {
                "type": "integer",
                "format": "int32"
              }
            }
          }
        },
        "responses": {
          "200": {
            "description": "OK"
          }
        }
      }
    },
    "/api/Game/all-users": {
      "get": {
        "tags": [
          "Game"
        ],
        "responses": {
          "200": {
            "description": "OK"
          }
        }
      }
    },
    "/api/Game/user": {
      "post": {
        "tags": [
          "Game"
        ],
        "requestBody": {
          "content": {
            "application/json": {
              "schema": {
                "$ref": "#/components/schemas/User"
              }
            },
            "text/json": {
              "schema": {
                "$ref": "#/components/schemas/User"
              }
            },
            "application/*+json": {
              "schema": {
                "$ref": "#/components/schemas/User"
              }
            }
          }
        },
        "responses": {
          "200": {
            "description": "OK"
          }
        }
      }
    },
    "/api/Game/login": {
      "post": {
        "tags": [
          "Game"
        ],
        "requestBody": {
          "content": {
            "application/json": {
              "schema": {
                "$ref": "#/components/schemas/User"
              }
            },
            "text/json": {
              "schema": {
                "$ref": "#/components/schemas/User"
              }
            },
            "application/*+json": {
              "schema": {
                "$ref": "#/components/schemas/User"
              }
            }
          }
        },
        "responses": {
          "200": {
            "description": "OK"
          }
        }
      }
    },
    "/api/Game/matches/{userId}": {
      "get": {
        "tags": [
          "Game"
        ],
        "parameters": [
          {
            "name": "userId",
            "in": "path",
            "required": true,
            "schema": {
              "type": "integer",
              "format": "int32"
            }
          }
        ],
        "responses": {
          "200": {
            "description": "OK"
          }
        }
      }
    },
    "/api/Game/match/{matchId}": {
      "get": {
        "tags": [
          "Game"
        ],
        "parameters": [
          {
            "name": "matchId",
            "in": "path",
            "required": true,
            "schema": {
              "type": "integer",
              "format": "int32"
            }
          }
        ],
        "responses": {
          "200": {
            "description": "OK"
          }
        }
      }
    },
    "/api/Game/move": {
      "post": {
        "tags": [
          "Game"
        ],
        "requestBody": {
          "content": {
            "application/json": {
              "schema": {
                "$ref": "#/components/schemas/GameRecord"
              }
            },
            "text/json": {
              "schema": {
                "$ref": "#/components/schemas/GameRecord"
              }
            },
            "application/*+json": {
              "schema": {
                "$ref": "#/components/schemas/GameRecord"
              }
            }
          }
        },
        "responses": {
          "200": {
            "description": "OK"
          }
        }
      }
    },
    "/api/Game/undo": {
      "post": {
        "tags": [
          "Game"
        ],
        "requestBody": {
          "content": {
            "application/json": {
              "schema": {
                "$ref": "#/components/schemas/GameRecord"
              }
            },
            "text/json": {
              "schema": {
                "$ref": "#/components/schemas/GameRecord"
              }
            },
            "application/*+json": {
              "schema": {
                "$ref": "#/components/schemas/GameRecord"
              }
            }
          }
        },
        "responses": {
          "200": {
            "description": "OK"
          }
        }
      }
    },
    "/api/Game/match/{matchId}/records": {
      "get": {
        "tags": [
          "Game"
        ],
        "parameters": [
          {
            "name": "matchId",
            "in": "path",
            "required": true,
            "schema": {
              "type": "integer",
              "format": "int32"
            }
          }
        ],
        "responses": {
          "200": {
            "description": "OK"
          }
        }
      }
    },
    "/api/Game/valid-moves": {
      "get": {
        "tags": [
          "Game"
        ],
        "parameters": [
          {
            "name": "fen",
            "in": "query",
            "schema": {
              "type": "string"
            }
          },
          {
            "name": "fromRow",
            "in": "query",
            "schema": {
              "type": "integer",
              "format": "int32"
            }
          },
          {
            "name": "fromCol",
            "in": "query",
            "schema": {
              "type": "integer",
              "format": "int32"
            }
          }
        ],
        "responses": {
          "200": {
            "description": "OK"
          }
        }
      }
    }
  },
  "components": {
    "schemas": {
      "GameRecord": {
        "type": "object",
        "properties": {
          "gameRecordId": {
            "type": "integer",
            "format": "int32"
          },
          "matchId": {
            "type": "integer",
            "format": "int32"
          },
          "fromRow": {
            "type": "integer",
            "format": "int32"
          },
          "toRow": {
            "type": "integer",
            "format": "int32"
          },
          "fromCol": {
            "type": "integer",
            "format": "int32"
          },
          "toCol": {
            "type": "integer",
            "format": "int32"
          },
          "isCapture": {
            "type": "boolean"
          },
          "isCastling": {
            "type": "boolean"
          },
          "isEnPassant": {
            "type": "boolean"
          },
          "promotion": {
            "type": "integer",
            "format": "int32",
            "nullable": true
          },
          "fenString": {
            "type": "string",
            "nullable": true
          },
          "moveNumber": {
            "type": "integer",
            "format": "int32"
          }
        },
        "additionalProperties": false
      },
      "Match": {
        "type": "object",
        "properties": {
          "matchId": {
            "type": "integer",
            "format": "int32"
          },
          "userId": {
            "type": "integer",
            "format": "int32"
          },
          "result": {
            "type": "integer",
            "format": "int32"
          },
          "status": {
            "type": "integer",
            "format": "int32"
          },
          "totalMoves": {
            "type": "integer",
            "format": "int32"
          }
        },
        "additionalProperties": false
      },
      "User": {
        "type": "object",
        "properties": {
          "userId": {
            "type": "integer",
            "format": "int32"
          },
          "userName": {
            "type": "string",
            "nullable": true
          }
        },
        "additionalProperties": false
      }
    }
  }
}